{"1":{"image":"071.png","answers":{"plastic":"4","rubber":"3","metallic":"2","fabric":"4","ceramic":"1","soft":"3","hard":"3","matte":"2","glossy":"4","bright":"3","rough":"2","refstrng":"4","refsharp":"3","reftint":"3"}},"2":{"image":"085.png","answers":{"plastic":"4","rubber":"2","metallic":"3","fabric":"4","ceramic":"3","soft":"2","hard":"3","matte":"4","glossy":"3","bright":"1","rough":"4","refstrng":"4","refsharp":"3","reftint":"4"}},"3":{"image":"blue-fabric_5PCs.png","answers":{"plastic":"2","rubber":"4","metallic":"2","fabric":"2","ceramic":"2","soft":"4","hard":"3","matte":"2","glossy":"3","bright":"3","rough":"1","refstrng":"3","refsharp":"3","reftint":"4"}},"4":{"image":"082.png","answers":{"plastic":"4","rubber":"2","metallic":"3","fabric":"4","ceramic":"3","soft":"2","hard":"2","matte":"3","glossy":"3","bright":"4","rough":"4","refstrng":"3","refsharp":"2","reftint":"3"}},"5":{"image":"108.png","answers":{"plastic":"2","rubber":"3","metallic":"4","fabric":"3","ceramic":"1","soft":"4","hard":"4","matte":"2","glossy":"3","bright":"4","rough":"4","refstrng":"3","refsharp":"2","reftint":"4"}},"6":{"image":"302.png","answers":{"plastic":"1","rubber":"2","metallic":"3","fabric":"2","ceramic":"4","soft":"3","hard":"2","matte":"4","glossy":"3","bright":"2","rough":"5","refstrng":"4","refsharp":"3","reftint":"3"}},"7":{"image":"gold-paint_5PCs.png","answers":{"plastic":"4","rubber":"3","metallic":"2","fabric":"3","ceramic":"3","soft":"4","hard":"2","matte":"4","glossy":"3","bright":"4","rough":"3","refstrng":"3","refsharp":"2","reftint":"4"}},"8":{"image":"orange-paint_5PCs.png","answers":{"plastic":"3","rubber":"2","metallic":"4","fabric":"3","ceramic":"2","soft":"4","hard":"3","matte":"2","glossy":"3","bright":"4","rough":"2","refstrng":"3","refsharp":"4","reftint":"3"}},"9":{"image":"277.png","answers":{"plastic":"4","rubber":"3","metallic":"2","fabric":"4","ceramic":"3","soft":"2","hard":"3","matte":"4","glossy":"4","bright":"3","rough":"5","refstrng":"3","refsharp":"4","reftint":"3"}},"10":{"image":"246.png","answers":{"plastic":"4","rubber":"3","metallic":"4","fabric":"2","ceramic":"3","soft":"4","hard":"3","matte":"2","glossy":"4","bright":"3","rough":"5","refstrng":"2","refsharp":"4","reftint":"3"}},"11":{"image":"209.png","answers":{"plastic":"5","rubber":"2","metallic":"4","fabric":"2","ceramic":"4","soft":"4","hard":"2","matte":"4","glossy":"3","bright":"2","rough":"1","refstrng":"4","refsharp":"4","reftint":"3"}},"12":{"token":"56913a8af22ca"},"13":{"listID":"list_020.txt"}}